dltk_ai/__init__.py
dltk_ai/assertions.py
dltk_ai/core.py
dltk_ai/data_preprocessing.py
dltk_ai/dataset_types.py
dltk_ai/helper.py
dltk_ai/ml_hyperparameters.py
dltk_ai/visualization.py
test/__init__.py
test/ml_tests/__init__.py
test/ml_tests/test_h2o_algo_assertions.py
test/ml_tests/test_scikit_algo_assertions.py
test/ml_tests/test_weka_algo_assertions.py
qubitai_dltk-1.0.9.dist-info/LICENSE
qubitai_dltk-1.0.9.dist-info/METADATA
qubitai_dltk-1.0.9.dist-info/WHEEL
qubitai_dltk-1.0.9.dist-info/top_level.txt
qubitai_dltk-1.0.9.dist-info/RECORD
