Metadata-Version: 2.1
Name: qubitai-dltk
Version: 1.0.9
Summary: Python Client for DLTK.
Home-page: https://github.com/dltk-ai/qubitai-dltk
Author: DLTK
Author-email: connect@qubitai.tech
License: UNKNOWN
Platform: UNKNOWN
Classifier: Programming Language :: Python :: 3
Classifier: License :: OSI Approved :: MIT License
Classifier: Operating System :: OS Independent
License-File: LICENSE
Requires-Dist: pandas (==1.2.3)
Requires-Dist: xlrd (==2.0.1)
Requires-Dist: matplotlib (==3.3.2)
Requires-Dist: numpy (==1.20.2)
Requires-Dist: requests (==2.25.1)
Requires-Dist: openpyxl (==3.0.7)
Requires-Dist: certifi (==2020.12.5)
Requires-Dist: pandas-profiling (==2.11.0)
Requires-Dist: seaborn (==0.11.1)
Requires-Dist: scikit-learn (==0.24.1)
Requires-Dist: autoviz (==0.0.81)
Requires-Dist: dtale (==1.41.1)
Requires-Dist: umap-learn (==0.5.1)
